{
  "schemaVersion": 1,
  "id": "emotion",
  "version": "${version}",
  "name": "Emotion",
  "description": "A unique cheat for 2B2T",
  "authors": [],
  "contact": {},
  "license": "All-Rights-Reserved",
  "icon": "assets/emotion/icon.png",
  "environment": "client",
  "entrypoints": {
    "main": [
      "cc.emotion.Emotion"
    ]
  },
  "mixins": [
    "emotion.mixins.json"
  ],
  "depends": {
    "fabricloader": ">=${loader_version}",
    "fabric": "*",
    "minecraft": "${minecraft_version}"
  }
}
